{"config":{"output_file":null,"full_docs":false,"pub_only":true,"reachable_only":true,"distro_crate":false,"signatures":false,"borrow_data":false},"version":"0.19.1","compilation":{"directory":"/Users/hao/.cargo/registry/src/github.com-1ecc6299db9ec823/pbkdf2-0.4.0","program":"/Users/hao/.rustup/toolchains/stable-aarch64-apple-darwin/bin/rls","arguments":["--crate-name","pbkdf2","--edition=2018","/Users/hao/.cargo/registry/src/github.com-1ecc6299db9ec823/pbkdf2-0.4.0/src/lib.rs","--json=diagnostic-rendered-ansi","--crate-type","lib","--emit=dep-info,metadata","-C","embed-bitcode=no","-C","split-debuginfo=unpacked","-C","debuginfo=2","-C","metadata=82ec767106ffbe9f","-C","extra-filename=-82ec767106ffbe9f","--out-dir","/Users/hao/Code/substrate/course/lesson_1/pallets/template/target/rls/debug/deps","-L","dependency=/Users/hao/Code/substrate/course/lesson_1/pallets/template/target/rls/debug/deps","--extern","crypto_mac=/Users/hao/Code/substrate/course/lesson_1/pallets/template/target/rls/debug/deps/libcrypto_mac-c82dbe037b90e004.rmeta","--cap-lints","allow","--error-format=json","--sysroot","/Users/hao/.rustup/toolchains/stable-aarch64-apple-darwin"],"output":"/Users/hao/Code/substrate/course/lesson_1/pallets/template/target/rls/debug/deps/libpbkdf2-82ec767106ffbe9f.rmeta"},"prelude":{"crate_id":{"name":"pbkdf2","disambiguator":[9390370027550788766,556166852551285077]},"crate_root":"/Users/hao/.cargo/registry/src/github.com-1ecc6299db9ec823/pbkdf2-0.4.0/src","external_crates":[{"file_name":"/Users/hao/.cargo/registry/src/github.com-1ecc6299db9ec823/pbkdf2-0.4.0/src/lib.rs","num":1,"id":{"name":"core","disambiguator":[2926027659608477847,13266562012387424727]}},{"file_name":"/Users/hao/.cargo/registry/src/github.com-1ecc6299db9ec823/pbkdf2-0.4.0/src/lib.rs","num":2,"id":{"name":"compiler_builtins","disambiguator":[16543572953398241612,13462986764070019698]}},{"file_name":"/Users/hao/.cargo/registry/src/github.com-1ecc6299db9ec823/pbkdf2-0.4.0/src/lib.rs","num":3,"id":{"name":"rustc_std_workspace_core","disambiguator":[8178771900672787435,15547668090406144857]}},{"file_name":"/Users/hao/.cargo/registry/src/github.com-1ecc6299db9ec823/pbkdf2-0.4.0/src/lib.rs","num":4,"id":{"name":"crypto_mac","disambiguator":[5587959749426694438,5746456772436104890]}},{"file_name":"/Users/hao/.cargo/registry/src/github.com-1ecc6299db9ec823/pbkdf2-0.4.0/src/lib.rs","num":5,"id":{"name":"generic_array","disambiguator":[2337757577070701638,14044355793205228084]}},{"file_name":"/Users/hao/.cargo/registry/src/github.com-1ecc6299db9ec823/pbkdf2-0.4.0/src/lib.rs","num":6,"id":{"name":"typenum","disambiguator":[12196112343123066798,15253588134102073309]}},{"file_name":"/Users/hao/.cargo/registry/src/github.com-1ecc6299db9ec823/pbkdf2-0.4.0/src/lib.rs","num":7,"id":{"name":"subtle","disambiguator":[4361875209938017689,7777186720441089215]}},{"file_name":"/Users/hao/.cargo/registry/src/github.com-1ecc6299db9ec823/pbkdf2-0.4.0/src/lib.rs","num":8,"id":{"name":"std","disambiguator":[16841035755873987138,8908851700613744445]}},{"file_name":"/Users/hao/.cargo/registry/src/github.com-1ecc6299db9ec823/pbkdf2-0.4.0/src/lib.rs","num":9,"id":{"name":"alloc","disambiguator":[9156920429250817125,11075234384113967897]}},{"file_name":"/Users/hao/.cargo/registry/src/github.com-1ecc6299db9ec823/pbkdf2-0.4.0/src/lib.rs","num":10,"id":{"name":"libc","disambiguator":[11279596189188458369,12350340105194636324]}},{"file_name":"/Users/hao/.cargo/registry/src/github.com-1ecc6299db9ec823/pbkdf2-0.4.0/src/lib.rs","num":11,"id":{"name":"unwind","disambiguator":[7312015018221179255,4742041386565820272]}},{"file_name":"/Users/hao/.cargo/registry/src/github.com-1ecc6299db9ec823/pbkdf2-0.4.0/src/lib.rs","num":12,"id":{"name":"cfg_if","disambiguator":[15891109833083679534,17984379632392221749]}},{"file_name":"/Users/hao/.cargo/registry/src/github.com-1ecc6299db9ec823/pbkdf2-0.4.0/src/lib.rs","num":13,"id":{"name":"hashbrown","disambiguator":[16902119159609667480,6524026496945547584]}},{"file_name":"/Users/hao/.cargo/registry/src/github.com-1ecc6299db9ec823/pbkdf2-0.4.0/src/lib.rs","num":14,"id":{"name":"rustc_std_workspace_alloc","disambiguator":[3621897933862434564,16562186117073056480]}},{"file_name":"/Users/hao/.cargo/registry/src/github.com-1ecc6299db9ec823/pbkdf2-0.4.0/src/lib.rs","num":15,"id":{"name":"rustc_demangle","disambiguator":[15536936008295295249,10906270311338372224]}},{"file_name":"/Users/hao/.cargo/registry/src/github.com-1ecc6299db9ec823/pbkdf2-0.4.0/src/lib.rs","num":16,"id":{"name":"std_detect","disambiguator":[10382820985286059075,14577866580883878825]}},{"file_name":"/Users/hao/.cargo/registry/src/github.com-1ecc6299db9ec823/pbkdf2-0.4.0/src/lib.rs","num":17,"id":{"name":"addr2line","disambiguator":[14597332125720628794,2125191253906842166]}},{"file_name":"/Users/hao/.cargo/registry/src/github.com-1ecc6299db9ec823/pbkdf2-0.4.0/src/lib.rs","num":18,"id":{"name":"gimli","disambiguator":[8450432001629562665,933745348923591991]}},{"file_name":"/Users/hao/.cargo/registry/src/github.com-1ecc6299db9ec823/pbkdf2-0.4.0/src/lib.rs","num":19,"id":{"name":"object","disambiguator":[16715270918519391585,15765631768114097577]}},{"file_name":"/Users/hao/.cargo/registry/src/github.com-1ecc6299db9ec823/pbkdf2-0.4.0/src/lib.rs","num":20,"id":{"name":"panic_unwind","disambiguator":[3555059470230282113,9390402421115331706]}}],"span":{"file_name":"/Users/hao/.cargo/registry/src/github.com-1ecc6299db9ec823/pbkdf2-0.4.0/src/lib.rs","byte_start":0,"byte_end":2658,"line_start":1,"line_end":97,"column_start":1,"column_end":2}},"imports":[],"defs":[{"kind":"Mod","id":{"krate":0,"index":0},"span":{"file_name":"/Users/hao/.cargo/registry/src/github.com-1ecc6299db9ec823/pbkdf2-0.4.0/src/lib.rs","byte_start":0,"byte_end":2658,"line_start":1,"line_end":97,"column_start":1,"column_end":2},"name":"","qualname":"::","value":"/Users/hao/.cargo/registry/src/github.com-1ecc6299db9ec823/pbkdf2-0.4.0/src/lib.rs","parent":null,"children":[{"krate":0,"index":1},{"krate":0,"index":2},{"krate":0,"index":3},{"krate":0,"index":4},{"krate":0,"index":7},{"krate":0,"index":8},{"krate":0,"index":11},{"krate":0,"index":14},{"krate":0,"index":16},{"krate":0,"index":18}],"decl_id":null,"docs":" This crate implements the PBKDF2 key derivation function as specified\n in [RFC 2898](https://tools.ietf.org/html/rfc2898).","sig":null,"attributes":[{"value":"/ This crate implements the PBKDF2 key derivation function as specified","span":{"file_name":"/Users/hao/.cargo/registry/src/github.com-1ecc6299db9ec823/pbkdf2-0.4.0/src/lib.rs","byte_start":0,"byte_end":73,"line_start":1,"line_end":1,"column_start":1,"column_end":74}},{"value":"/ in [RFC 2898](https://tools.ietf.org/html/rfc2898).","span":{"file_name":"/Users/hao/.cargo/registry/src/github.com-1ecc6299db9ec823/pbkdf2-0.4.0/src/lib.rs","byte_start":74,"byte_end":129,"line_start":2,"line_end":2,"column_start":1,"column_end":56}},{"value":"/","span":{"file_name":"/Users/hao/.cargo/registry/src/github.com-1ecc6299db9ec823/pbkdf2-0.4.0/src/lib.rs","byte_start":130,"byte_end":133,"line_start":3,"line_end":3,"column_start":1,"column_end":4}},{"value":"/ If you are not using convinience functions `pbkdf2_check` and `pbkdf2_simple`","span":{"file_name":"/Users/hao/.cargo/registry/src/github.com-1ecc6299db9ec823/pbkdf2-0.4.0/src/lib.rs","byte_start":134,"byte_end":215,"line_start":4,"line_end":4,"column_start":1,"column_end":82}},{"value":"/ it's recommended to disable `pbkdf2` default features in your `Cargo.toml`:","span":{"file_name":"/Users/hao/.cargo/registry/src/github.com-1ecc6299db9ec823/pbkdf2-0.4.0/src/lib.rs","byte_start":216,"byte_end":295,"line_start":5,"line_end":5,"column_start":1,"column_end":80}},{"value":"/ ```toml","span":{"file_name":"/Users/hao/.cargo/registry/src/github.com-1ecc6299db9ec823/pbkdf2-0.4.0/src/lib.rs","byte_start":296,"byte_end":307,"line_start":6,"line_end":6,"column_start":1,"column_end":12}},{"value":"/ [dependencies]","span":{"file_name":"/Users/hao/.cargo/registry/src/github.com-1ecc6299db9ec823/pbkdf2-0.4.0/src/lib.rs","byte_start":308,"byte_end":326,"line_start":7,"line_end":7,"column_start":1,"column_end":19}},{"value":"/ pbkdf2 = { version = \"0.2\", default-features = false }","span":{"file_name":"/Users/hao/.cargo/registry/src/github.com-1ecc6299db9ec823/pbkdf2-0.4.0/src/lib.rs","byte_start":327,"byte_end":385,"line_start":8,"line_end":8,"column_start":1,"column_end":59}},{"value":"/ ```","span":{"file_name":"/Users/hao/.cargo/registry/src/github.com-1ecc6299db9ec823/pbkdf2-0.4.0/src/lib.rs","byte_start":386,"byte_end":393,"line_start":9,"line_end":9,"column_start":1,"column_end":8}},{"value":"no_std","span":{"file_name":"/Users/hao/.cargo/registry/src/github.com-1ecc6299db9ec823/pbkdf2-0.4.0/src/lib.rs","byte_start":394,"byte_end":404,"line_start":10,"line_end":10,"column_start":1,"column_end":11}}]},{"kind":"Function","id":{"krate":0,"index":18},"span":{"file_name":"/Users/hao/.cargo/registry/src/github.com-1ecc6299db9ec823/pbkdf2-0.4.0/src/lib.rs","byte_start":2310,"byte_end":2316,"line_start":87,"line_end":87,"column_start":8,"column_end":14},"name":"pbkdf2","qualname":"::pbkdf2","value":"pub fn pbkdf2<F>(&[u8], &[u8], u32, &mut [u8]) where F: Mac + NewMac + Clone +\nSync","parent":null,"children":[],"decl_id":null,"docs":" Generic implementation of PBKDF2 algorithm.\n","sig":null,"attributes":[{"value":"/ Generic implementation of PBKDF2 algorithm.","span":{"file_name":"/Users/hao/.cargo/registry/src/github.com-1ecc6299db9ec823/pbkdf2-0.4.0/src/lib.rs","byte_start":2211,"byte_end":2258,"line_start":84,"line_end":84,"column_start":1,"column_end":48}},{"value":"cfg(not(feature = \"parallel\"))","span":{"file_name":"/Users/hao/.cargo/registry/src/github.com-1ecc6299db9ec823/pbkdf2-0.4.0/src/lib.rs","byte_start":2259,"byte_end":2292,"line_start":85,"line_end":85,"column_start":1,"column_end":34}},{"value":"inline","span":{"file_name":"/Users/hao/.cargo/registry/src/github.com-1ecc6299db9ec823/pbkdf2-0.4.0/src/lib.rs","byte_start":2293,"byte_end":2302,"line_start":86,"line_end":86,"column_start":1,"column_end":10}}]}],"impls":[],"refs":[],"macro_refs":[],"relations":[]}